alignment_train_cpu_binding.cp310-win_amd64.pyd
fairseq/__init__.py
fairseq/binarizer.py
fairseq/checkpoint_utils.py
fairseq/file_chunker_utils.py
fairseq/file_io.py
fairseq/file_utils.py
fairseq/hub_utils.py
fairseq/incremental_decoding_utils.py
fairseq/iterative_refinement_generator.py
fairseq/libbase.cp310-win_amd64.pyd
fairseq/libbleu.cp310-win_amd64.pyd
fairseq/libnat.cp310-win_amd64.pyd
fairseq/nan_detector.py
fairseq/ngram_repeat_block.py
fairseq/options.py
fairseq/pdb.py
fairseq/quantization_utils.py
fairseq/registry.py
fairseq/search.py
fairseq/sequence_generator.py
fairseq/sequence_scorer.py
fairseq/speech_generator.py
fairseq/token_generation_constraints.py
fairseq/tokenizer.py
fairseq/trainer.py
fairseq/utils.py
fairseq/version.py
fairseq/benchmark/__init__.py
fairseq/benchmark/benchmark_multihead_attention.py
fairseq/benchmark/dummy_dataset.py
fairseq/benchmark/dummy_lm.py
fairseq/benchmark/dummy_masked_lm.py
fairseq/benchmark/dummy_model.py
fairseq/benchmark/dummy_mt.py
fairseq/config/__init__.py
fairseq/config/config.yaml
fairseq/config/fb_run_config/slurm.yaml
fairseq/config/model/transformer_lm/transformer_lm_baevski_gbw.yaml
fairseq/config/model/transformer_lm/transformer_lm_baevski_wiki103.yaml
fairseq/config/model/transformer_lm/transformer_lm_big.yaml
fairseq/config/model/transformer_lm/transformer_lm_gbw.yaml
fairseq/config/model/transformer_lm/transformer_lm_gpt.yaml
fairseq/config/model/transformer_lm/transformer_lm_gpt2_big.yaml
fairseq/config/model/transformer_lm/transformer_lm_gpt2_medium.yaml
fairseq/config/model/transformer_lm/transformer_lm_gpt2_small.yaml
fairseq/config/model/transformer_lm/transformer_lm_wiki103.yaml
fairseq/config/model/wav2vec/vq_wav2vec_gumbel.yaml
fairseq/config/model/wav2vec2/wav2vec2_base.yaml
fairseq/config/model/wav2vec2/wav2vec2_large.yaml
fairseq/criterions/__init__.py
fairseq/criterions/adaptive_loss.py
fairseq/criterions/composite_loss.py
fairseq/criterions/cross_entropy.py
fairseq/criterions/ctc.py
fairseq_built-0.12.4.dist-info/licenses/LICENSE
fairseq_built-0.12.4.dist-info/METADATA
fairseq_built-0.12.4.dist-info/WHEEL
fairseq_built-0.12.4.dist-info/entry_points.txt
fairseq_built-0.12.4.dist-info/top_level.txt
fairseq_built-0.12.4.dist-info/RECORD
